inflection_jinja/__init__.py
inflection_jinja/inflection_jinja.py
inflection_jinja-0.1.0.dist-info/AUTHORS.rst
inflection_jinja-0.1.0.dist-info/LICENSE
inflection_jinja-0.1.0.dist-info/METADATA
inflection_jinja-0.1.0.dist-info/WHEEL
inflection_jinja-0.1.0.dist-info/top_level.txt
inflection_jinja-0.1.0.dist-info/RECORD
