Metadata-Version: 2.1
Name: inflection-jinja
Version: 0.1.0
Summary: Jinja extension wrapping infection package.
Home-page: https://github.com/macher91/inflection_jinja
Author: Mateusz Mejsner
Author-email: mateusz.mejsner@gmail.com
License: BSD license
Keywords: inflection_jinja
Platform: UNKNOWN
Classifier: Development Status :: 2 - Pre-Alpha
Classifier: Intended Audience :: Developers
Classifier: License :: OSI Approved :: BSD License
Classifier: Natural Language :: English
Classifier: Programming Language :: Python :: 3
Classifier: Programming Language :: Python :: 3.4
Classifier: Programming Language :: Python :: 3.5
Classifier: Programming Language :: Python :: 3.6
Classifier: Programming Language :: Python :: 3.7
Requires-Dist: jinja2 (==2.10)
Requires-Dist: inflection (==0.3.1)
